pbipy/__init__.py
pbipy/__version__.py
pbipy/_utils.py
pbipy/admin.py
pbipy/apps.py
pbipy/dashboards.py
pbipy/dataflows.py
pbipy/datasets.py
pbipy/embedtokens.py
pbipy/gateways.py
pbipy/groups.py
pbipy/imports.py
pbipy/powerbi.py
pbipy/reports.py
pbipy/resources.py
pbipy/settings.py
pbipy-2.13.0.dist-info/LICENSE
pbipy-2.13.0.dist-info/METADATA
pbipy-2.13.0.dist-info/WHEEL
pbipy-2.13.0.dist-info/top_level.txt
pbipy-2.13.0.dist-info/RECORD
