Metadata-Version: 2.1
Name: pbipy
Version: 2.13.0
Summary: A Python Library for interacting with the Power BI Rest API.
Home-page: https://github.com/andrewvillazon/pbipy
Author: Andrew Villazon
Author-email: andrew.villazon@gmail.com
License: Apache 2.0
Classifier: License :: OSI Approved :: Apache Software License
Classifier: Programming Language :: Python
Classifier: Programming Language :: Python :: 3
Classifier: Programming Language :: Python :: 3.10
Classifier: Programming Language :: Python :: Implementation :: CPython
Classifier: Programming Language :: Python :: Implementation :: PyPy
Classifier: Intended Audience :: System Administrators
Requires-Python: >=3.10
License-File: LICENSE
Requires-Dist: python-dateutil (>=2.8.2)
Requires-Dist: requests (>=2.28.1)
Provides-Extra: dev
Requires-Dist: black ; extra == 'dev'
